{
  "id": "16-the-first-peloponnesian-war-461-446-bce",
  "title": "16. The First Peloponnesian War, 461–446 BCE",
  "description": "The causes, campaigns, and consequences of Athens’ conflict with Sparta and its allies during the First Peloponnesian War.",
  "questions": [
    {
      "question": "Between which years did the First Peloponnesian War take place?",
      "options": [
        "457–431 BCE",
        "464–454 BCE",
        "459–445 BCE",
        "461–446 BCE"
      ],
      "correctIndex": 3
    },
    {
      "question": "Which two states were Athens primarily fighting at the start of the war?",
      "options": [
        "Corinth and Epidaurus",
        "Megara and Boeotia",
        "Aegina and Argos",
        "Sparta and Thebes"
      ],
      "correctIndex": 0
    },
    {
      "question": "Where was Athens defeated on land early in the conflict?",
      "options": [
        "Halieis",
        "Choroneia",
        "Tanagra",
        "Oenephyta"
      ],
      "correctIndex": 0
    },
    {
      "question": "Where did Athens win a naval battle against Corinth?",
      "options": [
        "Cecryphaleia",
        "Aegina",
        "Salamis",
        "Megara"
      ],
      "correctIndex": 0
    },
    {
      "question": "What caused war between Athens and Aegina in 458 BCE?",
      "options": [
        "Spartan command",
        "Persian involvement",
        "Megarian pressure",
        "Athenian aggression"
      ],
      "correctIndex": 3
    },
    {
      "question": "What followed Athens’ naval victory over Aegina?",
      "options": [
        "Siege of Aegina",
        "Immediate surrender",
        "Spartan withdrawal",
        "Peace treaty"
      ],
      "correctIndex": 0
    },
    {
      "question": "Why did Megara defect to Athens?",
      "options": [
        "Religious dispute",
        "Economic collapse",
        "Border war with Corinth",
        "Fear of Persia"
      ],
      "correctIndex": 2
    },
    {
      "question": "Why was Megara’s defection strategically dangerous?",
      "options": [
        "It isolated Corinth",
        "It weakened Athens’ navy",
        "It risked war with Sparta",
        "It threatened Delos"
      ],
      "correctIndex": 2
    },
    {
      "question": "How did Athens respond when Corinth attacked Megara?",
      "options": [
        "Sent mercenaries",
        "Asked Sparta for help",
        "Did nothing",
        "Sent oldest and youngest hoplites"
      ],
      "correctIndex": 3
    },
    {
      "question": "What was the outcome of the fighting between Athens and Corinth in 458 BCE?",
      "options": [
        "Stalemate",
        "Athenian victory",
        "Corinthian victory",
        "Spartan intervention"
      ],
      "correctIndex": 1
    },
    {
      "question": "Which battle gave Athens a land empire in central Greece?",
      "options": [
        "Choroneia",
        "Halieis",
        "Oenephyta",
        "Tanagra"
      ],
      "correctIndex": 2
    },
    {
      "question": "Which regions formed Athens’ land empire after Oenephyta?",
      "options": [
        "Peloponnese and Doris",
        "Boeotia, Phocis, and Opuntian Locris",
        "Thrace and Macedonia",
        "Attica and Megara"
      ],
      "correctIndex": 1
    },
    {
      "question": "At which battle did Sparta defeat Athens in 457 BCE?",
      "options": [
        "Oenephyta",
        "Tanagra",
        "Halieis",
        "Chaeroneia"
      ],
      "correctIndex": 1
    },
    {
      "question": "Why did Sparta cross into Doris before the Battle of Tanagra?",
      "options": [
        "To restore control of Delphi",
        "To defend the Phocians",
        "To attack Athens",
        "To restore Doris’ freedom"
      ],
      "correctIndex": 3
    },
    {
      "question": "What did Athens do immediately after its defeat at Tanagra?",
      "options": [
        "Attacked Sparta",
        "Sought peace",
        "Defeated Boeotians at Oenephyta",
        "Abandoned Boeotia"
      ],
      "correctIndex": 2
    },
    {
      "question": "Which actions show Athens on the offensive in the Peloponnese?",
      "options": [
        "Attacking Corinth alone",
        "Besieging Thebes",
        "Burning dockyards and defeating Sicyon",
        "Invading Persia"
      ],
      "correctIndex": 2
    },
    {
      "question": "Which Spartan dockyard was probably burned by Athens?",
      "options": [
        "Gythium",
        "Corinth",
        "Pylos",
        "Nauplia"
      ],
      "correctIndex": 0
    },
    {
      "question": "What was the Sacred War of 448 BCE about?",
      "options": [
        "Control of Corinth",
        "Control of Delphi",
        "Control of Megara",
        "Control of Athens"
      ],
      "correctIndex": 1
    },
    {
      "question": "What happened at the Battle of Choroneia in 447 BCE?",
      "options": [
        "Athenian defeat and loss of Boeotia",
        "Spartan surrender",
        "Persian intervention",
        "Athenian victory"
      ],
      "correctIndex": 0
    },
    {
      "question": "What was the result of Athens’ defeat at Choroneia?",
      "options": [
        "Peace with Boeotia",
        "Expansion of empire",
        "Collapse of control over central Greece",
        "Immediate war with Sparta"
      ],
      "correctIndex": 2
    },
    {
      "question": "Who negotiated the Five Year Peace with Sparta?",
      "options": [
        "Themistocles",
        "Cimon",
        "Pericles",
        "Ephialtes"
      ],
      "correctIndex": 1
    },
    {
      "question": "In which year was the Five Year Peace agreed?",
      "options": [
        "451 BCE",
        "446 BCE",
        "448 BCE",
        "454 BCE"
      ],
      "correctIndex": 0
    },
    {
      "question": "Why was Cimon chosen to negotiate the peace?",
      "options": [
        "He was anti-Spartan",
        "He had pro-Spartan credentials",
        "He was a general in Egypt",
        "He supported Persia"
      ],
      "correctIndex": 1
    },
    {
      "question": "What did the Five Year Peace attempt to achieve?",
      "options": [
        "Delay further conflict between Athens and Sparta",
        "Create a joint empire",
        "Disband the Delian League",
        "End all conflict permanently"
      ],
      "correctIndex": 0
    },
    {
      "question": "What does the First Peloponnesian War demonstrate about Athens?",
      "options": [
        "Isolation from Greek affairs",
        "Reliance on Sparta",
        "Aggressive and expansionist policy",
        "Naval weakness"
      ],
      "correctIndex": 2
    }
  ]
}